XiaoqiangUpdater/__init__.py
XiaoqiangUpdater/pack_to_exe.py
XiaoqiangUpdater/updater.py
XiaoqiangUpdater/img/__init__.py
XiaoqiangUpdater/img/updater_logo.ico
XiaoqiangUpdater/img/updater_logo.png
img/__init__.py
XiaoqiangUpdater-1.0.1.dist-info/LICENSE
XiaoqiangUpdater-1.0.1.dist-info/METADATA
XiaoqiangUpdater-1.0.1.dist-info/WHEEL
XiaoqiangUpdater-1.0.1.dist-info/entry_points.txt
XiaoqiangUpdater-1.0.1.dist-info/top_level.txt
XiaoqiangUpdater-1.0.1.dist-info/RECORD
