Metadata-Version: 2.1
Name: XiaoqiangUpdater
Version: 1.0.1
Summary: A general purpose program upgrade tool
Home-page: https://github.com/xiaoqiangclub/XiaoqiangUpdater
Author: XiaoqiangClub
Author-email: xiaoqiangclub@hotmail.com
Classifier: Programming Language :: Python :: 3
Classifier: License :: OSI Approved :: Apache Software License
Classifier: Operating System :: OS Independent
Requires-Python: >=3.6
License-File: LICENSE
Requires-Dist: psutil
Requires-Dist: requests
Requires-Dist: pyinstaller
